pywith/__init__.py
pywith/main.py
pywith-0.1.0.dist-info/WHEEL
pywith-0.1.0.dist-info/entry_points.txt
pywith-0.1.0.dist-info/METADATA
pywith-0.1.0.dist-info/RECORD
